CLASSIFIERS
MANIFEST.in
README.md
VERSION
setup.py
gumshoe/__init__.py
gumshoe/admin.py
gumshoe/models.py
gumshoe/renderers.py
gumshoe/tests.py
gumshoe/urls.py
gumshoe/views.py
gumshoe.egg-info/PKG-INFO
gumshoe.egg-info/SOURCES.txt
gumshoe.egg-info/dependency_links.txt
gumshoe.egg-info/entry_points.txt
gumshoe.egg-info/requires.txt
gumshoe.egg-info/top_level.txt
gumshoe/fixtures/initial_data.json
gumshoe/management/__init__.py
gumshoe/management/commands/__init__.py
gumshoe/management/commands/import_bugzilla.py
gumshoe/south_migrations/0001_initial.py
gumshoe/south_migrations/__init__.py
gumshoe/standalone/__init__.py
gumshoe/standalone/commands.py
gumshoe/standalone/middleware.py
gumshoe/standalone/settings.py
gumshoe/standalone/settings_test.py
gumshoe/standalone/urls.py
gumshoe/standalone/wsgi.py
gumshoe/static/css/ie.css
gumshoe/static/css/issue-list.css
gumshoe/static/css/login.css
gumshoe/static/css/navbar.css
gumshoe/static/css/print.css
gumshoe/static/css/screen.css
gumshoe/static/css/update-issue.css
gumshoe/static/js/URI.js
gumshoe/static/js/angular.js
gumshoe/static/js/gumshoe.js
gumshoe/static/js/gumshoe.ng.js
gumshoe/static/js/test.url.js
gumshoe/static/js/ui-bootstrap-custom-0.10.0.js
gumshoe/templates/base.html
gumshoe/templates/ng-base.html
gumshoe/templates/gumshoe/issue-list.html
gumshoe/templates/gumshoe/login.html
gumshoe/templates/gumshoe/navbar.html
gumshoe/templates/gumshoe/update-issue.html
gumshoe/templates/tests/test-main.html