Metadata-Version: 1.1
Name: gumshoe
Version: 0.0.2
Summary: Issue tracking app based on django.
Home-page: https://github.com/nickswebsite/gumshoe
Author: The Magnificant Nick
Author-email: send_me_spam@yahoo.com
License: UNKNOWN
Platform: UNKNOWN
Classifier: Development Status :: 2 - Pre-Alpha
Classifier: Intended Audience :: Developers
Classifier: Intended Audience :: Information Technology
Classifier: Intended Audience :: System Administrators
Classifier: License :: Public Domain
Classifier: Operating System :: POSIX :: Linux
Classifier: Programming Language :: Python
Classifier: Topic :: Internet :: WWW/HTTP :: Dynamic Content
Classifier: Topic :: Office/Business :: Scheduling
Classifier: Topic :: Software Development
